ospd/__init__.py
ospd/__version__.py
ospd/command/__init__.py
ospd/command/command.py
ospd/command/initsubclass.py
ospd/command/registry.py
ospd/config.py
ospd/cvss.py
ospd/datapickler.py
ospd/errors.py
ospd/logger.py
ospd/main.py
ospd/misc.py
ospd/network.py
ospd/ospd.py
ospd/ospd_ssh.py
ospd/parser.py
ospd/protocol.py
ospd/resultlist.py
ospd/scan.py
ospd/server.py
ospd/timer.py
ospd/vtfilter.py
ospd/vts.py
ospd/xml.py
ospd-21.4.3.dist-info/COPYING
ospd-21.4.3.dist-info/WHEEL
ospd-21.4.3.dist-info/METADATA
ospd-21.4.3.dist-info/RECORD
