Metadata-Version: 2.1
Name: ospd
Version: 21.4.3
Summary: OSPD is a base for scanner wrappers which share the same communication protocol: OSP (Open Scanner Protocol)
Home-page: https://github.com/greenbone/ospd
License: AGPL-3.0-or-later
Keywords: Greenbone Vulnerability Management,Vulnerability Scanner,Open Scanner Protocol,OSP
Author: Greenbone Networks GmbH
Author-email: info@greenbone.net
Requires-Python: >=3.7,<4.0
Classifier: Development Status :: 4 - Beta
Classifier: Intended Audience :: Developers
Classifier: Intended Audience :: System Administrators
Classifier: License :: OSI Approved :: GNU Affero General Public License v3 or later (AGPLv3+)
Classifier: Programming Language :: Python :: 3
Classifier: Programming Language :: Python :: 3.7
Classifier: Programming Language :: Python :: 3.8
Classifier: Programming Language :: Python :: 3.9
Requires-Dist: defusedxml (>=0.6,<0.8)
Requires-Dist: deprecated (>=1.2.10,<2.0.0)
Requires-Dist: lxml (>=4.5.2,<5.0.0)
Requires-Dist: paramiko (>=2.7.1,<3.0.0)
Requires-Dist: psutil (>=5.7.2,<6.0.0)
Project-URL: Repository, https://github.com/greenbone/ospd
